{"id":"87","name":"Dewgong","types":["water","ice"],"height":5.58,"weight":264.55,"stats":[{"base":"90","name":"HP"},{"base":"70","name":"Attack"},{"base":"80","name":"Defense"},{"base":"70","name":"Sp. Attack"},{"base":"95","name":"Sp. Defense"},{"base":"70","name":"Speed"}],"previousPokemon":"seel","nextPokemon":"grimer","flavorText":"Stores thermal energy in its body. Swims at a steady 8 knots even in intensely cold waters.","colorPalette":{"Vibrant":[73.81578947368416,127.49999999999996,181.18421052631584],"DarkVibrant":[38.38421052631576,66.29999999999997,94.21578947368424],"LightVibrant":[228,236,244],"Muted":[122,126,130],"DarkMuted":[73,69,66],"LightMuted":[182,185,199]}}
