{"id":"2","slug":"ivysaur","types":["grass","poison"],"height":3.28,"weight":28.66,"stats":[{"base":"60","name":"HP"},{"base":"62","name":"Attack"},{"base":"63","name":"Defense"},{"base":"80","name":"Sp. Attack"},{"base":"80","name":"Sp. Defense"},{"base":"60","name":"Speed"}],"previousPokemon":"bulbasaur","nextPokemon":"venusaur","flavorText":"When the bulb on its back grows large, it appears to lose the ability to stand on its hind legs.","colorPalette":{"Vibrant":[196,52,92],"DarkVibrant":[27,98,115],"LightVibrant":[219,157,170],"Muted":[84,139,155],"DarkMuted":[48,76,61],"LightMuted":[124,186,189]}}
