{"id":"105","slug":"marowak","types":["ground"],"height":3.28,"weight":99.21,"stats":[{"base":"60","name":"HP"},{"base":"80","name":"Attack"},{"base":"110","name":"Defense"},{"base":"50","name":"Sp. Attack"},{"base":"80","name":"Sp. Defense"},{"base":"45","name":"Speed"}],"previousPokemon":"cubone","nextPokemon":"hitmonlee","flavorText":"The bone it holds is its key weapon. It throws the bone skillfully like a boomerang to KO targets.","colorPalette":{"Vibrant":[204,164,116],"DarkVibrant":[97.00736842105265,69.09157894736843,35.59263157894736],"LightVibrant":[236,220,204],"Muted":[148,123,91],"DarkMuted":[60,54,48],"LightMuted":[219,209,191]}}
