{"id":"38","name":"Ninetales","types":["fire"],"height":3.61,"weight":43.87,"stats":[{"base":"73","name":"HP"},{"base":"76","name":"Attack"},{"base":"75","name":"Defense"},{"base":"81","name":"Sp. Attack"},{"base":"100","name":"Sp. Defense"},{"base":"100","name":"Speed"}],"previousPokemon":"vulpix","nextPokemon":"jigglypuff","flavorText":"Very smart and very vengeful. Grabbing one of its many tails could result in a 1000-year curse.","colorPalette":{"Vibrant":[240,177,74],"DarkVibrant":[84,62,40],"LightVibrant":[252,247,165],"Muted":[165,109,81],"DarkMuted":[69,51,54],"LightMuted":[207,193,154]}}
