{"id":"46","name":"Paras","types":["bug","grass"],"height":0.98,"weight":11.9,"stats":[{"base":"35","name":"HP"},{"base":"70","name":"Attack"},{"base":"55","name":"Defense"},{"base":"45","name":"Sp. Attack"},{"base":"55","name":"Sp. Defense"},{"base":"25","name":"Speed"}],"previousPokemon":"vileplume","nextPokemon":"parasect","flavorText":"Burrows to suck tree roots. The mushrooms on its back grow by draw­ ing nutrients from the bug host.","colorPalette":{"Vibrant":[236,156,92],"DarkVibrant":[116,79,52],"LightVibrant":[244,204,148],"Muted":[171,114,88],"DarkMuted":[92,63,48],"LightMuted":[211,159,180]}}
