{"id":"134","slug":"vaporeon","types":["water"],"height":3.28,"weight":63.93,"stats":[{"base":"130","name":"HP"},{"base":"65","name":"Attack"},{"base":"60","name":"Defense"},{"base":"110","name":"Sp. Attack"},{"base":"95","name":"Sp. Defense"},{"base":"65","name":"Speed"}],"previousPokemon":"eevee","nextPokemon":"jolteon","flavorText":"Lives close to water. Its long tail is ridged with a fin which is often mistaken for a mermaid's.","colorPalette":{"Vibrant":[124,204,228],"DarkVibrant":[51,97,119],"LightVibrant":[145,211,227],"Muted":[99,155,171],"DarkMuted":[47,69,83],"LightMuted":[191,185,156]}}
